pysubsea/__init__.py
pysubsea/abaqus_tools.py
pysubsea/dnv_tools.py
pysubsea/lateral_buckling_tools.py
pysubsea/linepipe_tools.py
pysubsea/oos_tools.py
pysubsea/pipe_soil_interaction_tools.py
pysubsea-0.1.2.dist-info/licenses/LICENSE
pysubsea-0.1.2.dist-info/METADATA
pysubsea-0.1.2.dist-info/WHEEL
pysubsea-0.1.2.dist-info/top_level.txt
pysubsea-0.1.2.dist-info/RECORD
