Metadata-Version: 2.4
Name: pysubsea
Version: 0.1.2
Summary: Package for subsea pipelines and risers design in Python
Author-email: Ismael Ripoll <ismael.ripoll@subseaenergies.com>
License: MIT
Project-URL: Documentation, https://py-subsea.github.io/py-subsea/
Project-URL: Source, https://github.com/py-subsea/py-subsea
Project-URL: Tracker, https://github.com/py-subsea/py-subsea/issues
Keywords: subsea,pipeline,FEM,Python,engineering
Classifier: Programming Language :: Python :: 3
Classifier: Programming Language :: Python :: 3.10
Classifier: Programming Language :: Python :: 3.11
Classifier: License :: OSI Approved :: MIT License
Classifier: Operating System :: OS Independent
Classifier: Topic :: Scientific/Engineering
Requires-Python: >=3.10
License-File: LICENSE
Dynamic: license-file
